micro_rsa/__init__.py
micro_rsa/blinding.py
micro_rsa/common.py
micro_rsa/exceptions.py
micro_rsa/padding.py
micro_rsa/pkcs.py
micro_rsa/prime.py
micro_rsa/sieve_base.py
u_micro_rsa-2021.5.dist-info/LICENSE.txt
u_micro_rsa-2021.5.dist-info/METADATA
u_micro_rsa-2021.5.dist-info/WHEEL
u_micro_rsa-2021.5.dist-info/top_level.txt
u_micro_rsa-2021.5.dist-info/RECORD
